friend_lite/__init__.py
friend_lite/bluetooth.py
friend_lite/decoder.py
friend_lite/discover_characteristics.py
friend_lite/py.typed
friend_lite/transcribe.py
friend_lite_sdk-0.1.0.dist-info/METADATA
friend_lite_sdk-0.1.0.dist-info/WHEEL
friend_lite_sdk-0.1.0.dist-info/top_level.txt
friend_lite_sdk-0.1.0.dist-info/RECORD
