Metadata-Version: 2.4
Name: friend-lite-sdk
Version: 0.1.0
Summary: Friend Lite SDK
Project-URL: Homepage, https://github.com/AnkushMalaker/Friend
Requires-Python: >=3.10
Requires-Dist: aiohttp>=3.11.14
Requires-Dist: bleak>=0.22.3
Requires-Dist: httpx>=0.28.1
Requires-Dist: numpy>=1.26
Requires-Dist: opuslib>=3.0.1
Requires-Dist: websockets>=14.0.0
Provides-Extra: deepgram
Requires-Dist: deepgram-sdk>=3.11.0; extra == "deepgram"
Provides-Extra: dev
Requires-Dist: mypy>=1.15.0; extra == "dev"
Requires-Dist: mypy-extensions>=1.1.0; extra == "dev"
